mapshader/.version
mapshader/__init__.py
mapshader/colors.py
mapshader/core.py
mapshader/flask_app.py
mapshader/io.py
mapshader/mercator.py
mapshader/multifile.py
mapshader/overview.py
mapshader/renderers.py
mapshader/scan.py
mapshader/services.py
mapshader/sources.py
mapshader/tile_utils.py
mapshader/transforms.py
mapshader/utils.py
mapshader/wsgi.py
mapshader/commands/__init__.py
mapshader/commands/build_raster_overviews.py
mapshader/commands/examples.py
mapshader/commands/serve.py
mapshader/commands/tif_to_netcdf.py
mapshader/commands/tile.py
mapshader/examples/census_synthetic_people.yaml
mapshader/examples/elevation.tif
mapshader/examples/example-mapshader-config.yaml
mapshader/examples/large_geotiff.yaml
mapshader/examples/large_vrt.yaml
mapshader/examples/us_mountain_locations.yaml
mapshader/examples/world-cities-tiling-example.ipynb
mapshader/examples/world-countries-tiling-example.ipynb
mapshader/examples/world-elevation-tiling-example.ipynb
mapshader/templates/index_page.html
mapshader/templates/psutils.html
mapshader/templates/service_page.html
mapshader/tests/__init__.py
mapshader/tests/common.py
mapshader/tests/conftest.py
mapshader/tests/data.py
mapshader/tests/test_core.py
mapshader/tests/test_flask_app.py
mapshader/tests/test_io.py
mapshader/tests/test_large_geotiff.py
mapshader/tests/test_large_vrt.py
mapshader/tests/test_services_directory.py
mapshader/tests/test_sources.py
mapshader/tests/test_tif_to_netcdf.py
mapshader/tests/test_tile.py
mapshader/tests/test_tile_utils.py
mapshader/tests/test_transforms.py
mapshader/tests/fixtures/coastlines_wgs84.cpg
mapshader/tests/fixtures/coastlines_wgs84.dbf
mapshader/tests/fixtures/coastlines_wgs84.prj
mapshader/tests/fixtures/coastlines_wgs84.qpj
mapshader/tests/fixtures/coastlines_wgs84.shp
mapshader/tests/fixtures/coastlines_wgs84.shx
mapshader/tests/fixtures/counties_3857.gpkg
mapshader/tests/fixtures/counties_wgs84.cpg
mapshader/tests/fixtures/counties_wgs84.dbf
mapshader-0.1.3.dist-info/LICENSE
mapshader-0.1.3.dist-info/METADATA
mapshader-0.1.3.dist-info/WHEEL
mapshader-0.1.3.dist-info/entry_points.txt
mapshader-0.1.3.dist-info/top_level.txt
mapshader-0.1.3.dist-info/RECORD
