Metadata-Version: 2.1
Name: mapshader
Version: 0.1.3
Summary: Simple Python GIS Web Services
Home-page: https://github.com/makepath/mapshader
License: UNKNOWN
Platform: UNKNOWN
Classifier: Programming Language :: Python :: 3
Classifier: License :: OSI Approved :: MIT License
Classifier: Operating System :: OS Independent
Requires-Dist: bokeh (>=2.4.2)
Requires-Dist: xarray-spatial (>=0.3.5)
Requires-Dist: datashader (>=0.13.0)
Requires-Dist: geopandas (>=0.10.2)
Requires-Dist: dask-geopandas
Requires-Dist: click (>=8.0.3)
Requires-Dist: click-plugins (>=1.1.1)
Requires-Dist: jinja2 (>=3.0.3)
Requires-Dist: spatialpandas (>=0.4.3)
Requires-Dist: pytest (>=6.2.5)
Requires-Dist: rtree (>=0.9.7)
Requires-Dist: rioxarray (>=0.9.1)
Requires-Dist: matplotlib (>=3.5.1)
Requires-Dist: descartes (>=1.1.0)
Requires-Dist: flask (>=2.0.2)
Requires-Dist: flask-cors (>=3.0.10)
Requires-Dist: param (>=1.6.1)
Requires-Dist: rasterio (>=1.2.10)
Requires-Dist: jupyter (>=1.0.0)
Requires-Dist: pyarrow (>=6.0.1)
Requires-Dist: psutil (>=5.9.0)
Requires-Dist: pyct (>=0.4.6)
